{
    "generation": 9,
    "items": [
        {
            "address": "130.127.148.49",
            "description": "",
            "generation": 1,
            "kind": "tm:cloud:ltm:pool-members:ltmpoolmemberstate",
            "lastUpdateMicros": 0,
            "name": "130.127.148.49:6001",
            "nodeReference": {
                "link": "http://localhost/tm/cloud/ltm/node-addresses/Common/cortana"
            },
            "objectId": 37206,
            "port": 6001,
            "selfLink": "https://localhost/mgmt/tm/cloud/ltm/pool-members/37206",
            "statsContext": {
                "stats": [
                    {
                        "description": "availability_state: AVAIL_RED",
                        "lastUpdateMicros": 0,
                        "name": "health",
                        "updateType": "BASIC",
                        "value": 0.0
                    },
                    {
                        "description": "SERVERSIDE: pkts_in",
                        "lastUpdateMicros": 0,
                        "name": "serverside.pkts_in",
                        "updateType": "BASIC",
                        "value": 0.0
                    },
                    {
                        "description": "SERVERSIDE: pkts_out",
                        "lastUpdateMicros": 0,
                        "name": "serverside.pkts_out",
                        "updateType": "BASIC",
                        "value": 0.0
                    },
                    {
                        "description": "SERVERSIDE: bits-in",
                        "lastUpdateMicros": 0,
                        "name": "serverside.bits-in",
                        "updateType": "BASIC",
                        "value": 0.0
                    },
                    {
                        "description": "SERVERSIDE: bits-out",
                        "lastUpdateMicros": 0,
                        "name": "serverside.bits-out",
                        "updateType": "BASIC",
                        "value": 0.0
                    },
                    {
                        "description": "SERVERSIDE: cur_conns",
                        "lastUpdateMicros": 0,
                        "name": "serverside.cur_conns",
                        "updateType": "BASIC",
                        "value": 0.0
                    },
                    {
                        "description": "SERVERSIDE: max_conns",
                        "lastUpdateMicros": 0,
                        "name": "serverside.max_conns",
                        "updateType": "BASIC",
                        "value": 0.0
                    },
                    {
                        "description": "SERVERSIDE: tot_conns",
                        "lastUpdateMicros": 0,
                        "name": "serverside.tot_conns",
                        "updateType": "BASIC",
                        "value": 0.0
                    }
                ]
            }
        },
        {
            "address": "10.20.35.129",
            "description": "",
            "generation": 1,
            "kind": "tm:cloud:ltm:pool-members:ltmpoolmemberstate",
            "lastUpdateMicros": 0,
            "name": "10.20.35.129:80",
            "nodeReference": {
                "link": "http://localhost/tm/cloud/ltm/node-addresses/Common/devccittools01"
            },
            "objectId": 37210,
            "port": 80,
            "selfLink": "https://localhost/mgmt/tm/cloud/ltm/pool-members/37210",
            "statsContext": {
                "stats": [
                    {
                        "description": "availability_state: AVAIL_RED",
                        "lastUpdateMicros": 0,
                        "name": "health",
                        "updateType": "BASIC",
                        "value": 0.0
                    },
                    {
                        "description": "SERVERSIDE: pkts_in",
                        "lastUpdateMicros": 0,
                        "name": "serverside.pkts_in",
                        "updateType": "BASIC",
                        "value": 0.0
                    },
                    {
                        "description": "SERVERSIDE: pkts_out",
                        "lastUpdateMicros": 0,
                        "name": "serverside.pkts_out",
                        "updateType": "BASIC",
                        "value": 0.0
                    },
                    {
                        "description": "SERVERSIDE: bits-in",
                        "lastUpdateMicros": 0,
                        "name": "serverside.bits-in",
                        "updateType": "BASIC",
                        "value": 0.0
                    },
                    {
                        "description": "SERVERSIDE: bits-out",
                        "lastUpdateMicros": 0,
                        "name": "serverside.bits-out",
                        "updateType": "BASIC",
                        "value": 0.0
                    },
                    {
                        "description": "SERVERSIDE: cur_conns",
                        "lastUpdateMicros": 0,
                        "name": "serverside.cur_conns",
                        "updateType": "BASIC",
                        "value": 0.0
                    },
                    {
                        "description": "SERVERSIDE: max_conns",
                        "lastUpdateMicros": 0,
                        "name": "serverside.max_conns",
                        "updateType": "BASIC",
                        "value": 0.0
                    },
                    {
                        "description": "SERVERSIDE: tot_conns",
                        "lastUpdateMicros": 0,
                        "name": "serverside.tot_conns",
                        "updateType": "BASIC",
                        "value": 0.0
                    }
                ]
            }
        },
        {
            "address": "10.20.39.142",
            "description": "",
            "generation": 1,
            "kind": "tm:cloud:ltm:pool-members:ltmpoolmemberstate",
            "lastUpdateMicros": 0,
            "name": "10.20.39.142:80",
            "nodeReference": {
                "link": "http://localhost/tm/cloud/ltm/node-addresses/Common/devcogweb01.clemson.edu"
            },
            "objectId": 37214,
            "port": 80,
            "selfLink": "https://localhost/mgmt/tm/cloud/ltm/pool-members/37214",
            "statsContext": {
                "stats": [
                    {
                        "description": "availability_state: AVAIL_RED",
                        "lastUpdateMicros": 0,
                        "name": "health",
                        "updateType": "BASIC",
                        "value": 0.0
                    },
                    {
                        "description": "SERVERSIDE: pkts_in",
                        "lastUpdateMicros": 0,
                        "name": "serverside.pkts_in",
                        "updateType": "BASIC",
                        "value": 0.0
                    },
                    {
                        "description": "SERVERSIDE: pkts_out",
                        "lastUpdateMicros": 0,
                        "name": "serverside.pkts_out",
                        "updateType": "BASIC",
                        "value": 0.0
                    },
                    {
                        "description": "SERVERSIDE: bits-in",
                        "lastUpdateMicros": 0,
                        "name": "serverside.bits-in",
                        "updateType": "BASIC",
                        "value": 0.0
                    },
                    {
                        "description": "SERVERSIDE: bits-out",
                        "lastUpdateMicros": 0,
                        "name": "serverside.bits-out",
                        "updateType": "BASIC",
                        "value": 0.0
                    },
                    {
                        "description": "SERVERSIDE: cur_conns",
                        "lastUpdateMicros": 0,
                        "name": "serverside.cur_conns",
                        "updateType": "BASIC",
                        "value": 0.0
                    },
                    {
                        "description": "SERVERSIDE: max_conns",
                        "lastUpdateMicros": 0,
                        "name": "serverside.max_conns",
                        "updateType": "BASIC",
                        "value": 0.0
                    },
                    {
                        "description": "SERVERSIDE: tot_conns",
                        "lastUpdateMicros": 0,
                        "name": "serverside.tot_conns",
                        "updateType": "BASIC",
                        "value": 0.0
                    }
                ]
            }
        },
        {
            "address": "10.20.39.141",
            "description": "",
            "generation": 1,
            "kind": "tm:cloud:ltm:pool-members:ltmpoolmemberstate",
            "lastUpdateMicros": 0,
            "name": "10.20.39.141:80",
            "nodeReference": {
                "link": "http://localhost/tm/cloud/ltm/node-addresses/Common/devcogweb02.clemson.edu"
            },
            "objectId": 37217,
            "port": 80,
            "selfLink": "https://localhost/mgmt/tm/cloud/ltm/pool-members/37217",
            "statsContext": {
                "stats": [
                    {
                        "description": "availability_state: AVAIL_RED",
                        "lastUpdateMicros": 0,
                        "name": "health",
                        "updateType": "BASIC",
                        "value": 0.0
                    },
                    {
                        "description": "SERVERSIDE: pkts_in",
                        "lastUpdateMicros": 0,
                        "name": "serverside.pkts_in",
                        "updateType": "BASIC",
                        "value": 0.0
                    },
                    {
                        "description": "SERVERSIDE: pkts_out",
                        "lastUpdateMicros": 0,
                        "name": "serverside.pkts_out",
                        "updateType": "BASIC",
                        "value": 0.0
                    },
                    {
                        "description": "SERVERSIDE: bits-in",
                        "lastUpdateMicros": 0,
                        "name": "serverside.bits-in",
                        "updateType": "BASIC",
                        "value": 0.0
                    },
                    {
                        "description": "SERVERSIDE: bits-out",
                        "lastUpdateMicros": 0,
                        "name": "serverside.bits-out",
                        "updateType": "BASIC",
                        "value": 0.0
                    },
                    {
                        "description": "SERVERSIDE: cur_conns",
                        "lastUpdateMicros": 0,
                        "name": "serverside.cur_conns",
                        "updateType": "BASIC",
                        "value": 0.0
                    },
                    {
                        "description": "SERVERSIDE: max_conns",
                        "lastUpdateMicros": 0,
                        "name": "serverside.max_conns",
                        "updateType": "BASIC",
                        "value": 0.0
                    },
                    {
                        "description": "SERVERSIDE: tot_conns",
                        "lastUpdateMicros": 0,
                        "name": "serverside.tot_conns",
                        "updateType": "BASIC",
                        "value": 0.0
                    }
                ]
            }
        },
        {
            "address": "10.20.35.129",
            "description": "",
            "generation": 1,
            "kind": "tm:cloud:ltm:pool-members:ltmpoolmemberstate",
            "lastUpdateMicros": 0,
            "name": "10.20.35.129:6001",
            "nodeReference": {
                "link": "http://localhost/tm/cloud/ltm/node-addresses/Common/devccittools01"
            },
            "objectId": 37221,
            "port": 6001,
            "selfLink": "https://localhost/mgmt/tm/cloud/ltm/pool-members/37221",
            "statsContext": {
                "stats": [
                    {
                        "description": "availability_state: AVAIL_RED",
                        "lastUpdateMicros": 0,
                        "name": "health",
                        "updateType": "BASIC",
                        "value": 0.0
                    },
                    {
                        "description": "SERVERSIDE: pkts_in",
                        "lastUpdateMicros": 0,
                        "name": "serverside.pkts_in",
                        "updateType": "BASIC",
                        "value": 0.0
                    },
                    {
                        "description": "SERVERSIDE: pkts_out",
                        "lastUpdateMicros": 0,
                        "name": "serverside.pkts_out",
                        "updateType": "BASIC",
                        "value": 0.0
                    },
                    {
                        "description": "SERVERSIDE: bits-in",
                        "lastUpdateMicros": 0,
                        "name": "serverside.bits-in",
                        "updateType": "BASIC",
                        "value": 0.0
                    },
                    {
                        "description": "SERVERSIDE: bits-out",
                        "lastUpdateMicros": 0,
                        "name": "serverside.bits-out",
                        "updateType": "BASIC",
                        "value": 0.0
                    },
                    {
                        "description": "SERVERSIDE: cur_conns",
                        "lastUpdateMicros": 0,
                        "name": "serverside.cur_conns",
                        "updateType": "BASIC",
                        "value": 0.0
                    },
                    {
                        "description": "SERVERSIDE: max_conns",
                        "lastUpdateMicros": 0,
                        "name": "serverside.max_conns",
                        "updateType": "BASIC",
                        "value": 0.0
                    },
                    {
                        "description": "SERVERSIDE: tot_conns",
                        "lastUpdateMicros": 0,
                        "name": "serverside.tot_conns",
                        "updateType": "BASIC",
                        "value": 0.0
                    }
                ]
            }
        },
        {
            "address": "130.127.192.19",
            "description": "",
            "generation": 1,
            "kind": "tm:cloud:ltm:pool-members:ltmpoolmemberstate",
            "lastUpdateMicros": 0,
            "name": "130.127.192.19:80",
            "nodeReference": {
                "link": "http://localhost/tm/cloud/ltm/node-addresses/Common/shibsp3"
            },
            "objectId": 37225,
            "port": 80,
            "selfLink": "https://localhost/mgmt/tm/cloud/ltm/pool-members/37225",
            "statsContext": {
                "stats": [
                    {
                        "description": "availability_state: AVAIL_GREEN",
                        "lastUpdateMicros": 0,
                        "name": "health",
                        "updateType": "BASIC",
                        "value": 1.0
                    },
                    {
                        "description": "SERVERSIDE: pkts_in",
                        "lastUpdateMicros": 0,
                        "name": "serverside.pkts_in",
                        "updateType": "BASIC",
                        "value": 0.0
                    },
                    {
                        "description": "SERVERSIDE: pkts_out",
                        "lastUpdateMicros": 0,
                        "name": "serverside.pkts_out",
                        "updateType": "BASIC",
                        "value": 0.0
                    },
                    {
                        "description": "SERVERSIDE: bits-in",
                        "lastUpdateMicros": 0,
                        "name": "serverside.bits-in",
                        "updateType": "BASIC",
                        "value": 0.0
                    },
                    {
                        "description": "SERVERSIDE: bits-out",
                        "lastUpdateMicros": 0,
                        "name": "serverside.bits-out",
                        "updateType": "BASIC",
                        "value": 0.0
                    },
                    {
                        "description": "SERVERSIDE: cur_conns",
                        "lastUpdateMicros": 0,
                        "name": "serverside.cur_conns",
                        "updateType": "BASIC",
                        "value": 0.0
                    },
                    {
                        "description": "SERVERSIDE: max_conns",
                        "lastUpdateMicros": 0,
                        "name": "serverside.max_conns",
                        "updateType": "BASIC",
                        "value": 0.0
                    },
                    {
                        "description": "SERVERSIDE: tot_conns",
                        "lastUpdateMicros": 0,
                        "name": "serverside.tot_conns",
                        "updateType": "BASIC",
                        "value": 0.0
                    }
                ]
            }
        },
        {
            "address": "130.127.193.236",
            "description": "",
            "generation": 1,
            "kind": "tm:cloud:ltm:pool-members:ltmpoolmemberstate",
            "lastUpdateMicros": 0,
            "name": "130.127.193.236:80",
            "nodeReference": {
                "link": "http://localhost/tm/cloud/ltm/node-addresses/Common/shibsp4"
            },
            "objectId": 37228,
            "port": 80,
            "selfLink": "https://localhost/mgmt/tm/cloud/ltm/pool-members/37228",
            "statsContext": {
                "stats": [
                    {
                        "description": "availability_state: AVAIL_GREEN",
                        "lastUpdateMicros": 0,
                        "name": "health",
                        "updateType": "BASIC",
                        "value": 1.0
                    },
                    {
                        "description": "SERVERSIDE: pkts_in",
                        "lastUpdateMicros": 0,
                        "name": "serverside.pkts_in",
                        "updateType": "BASIC",
                        "value": 0.0
                    },
                    {
                        "description": "SERVERSIDE: pkts_out",
                        "lastUpdateMicros": 0,
                        "name": "serverside.pkts_out",
                        "updateType": "BASIC",
                        "value": 0.0
                    },
                    {
                        "description": "SERVERSIDE: bits-in",
                        "lastUpdateMicros": 0,
                        "name": "serverside.bits-in",
                        "updateType": "BASIC",
                        "value": 0.0
                    },
                    {
                        "description": "SERVERSIDE: bits-out",
                        "lastUpdateMicros": 0,
                        "name": "serverside.bits-out",
                        "updateType": "BASIC",
                        "value": 0.0
                    },
                    {
                        "description": "SERVERSIDE: cur_conns",
                        "lastUpdateMicros": 0,
                        "name": "serverside.cur_conns",
                        "updateType": "BASIC",
                        "value": 0.0
                    },
                    {
                        "description": "SERVERSIDE: max_conns",
                        "lastUpdateMicros": 0,
                        "name": "serverside.max_conns",
                        "updateType": "BASIC",
                        "value": 0.0
                    },
                    {
                        "description": "SERVERSIDE: tot_conns",
                        "lastUpdateMicros": 0,
                        "name": "serverside.tot_conns",
                        "updateType": "BASIC",
                        "value": 0.0
                    }
                ]
            }
        },
        {
            "address": "130.127.192.133",
            "description": "",
            "generation": 1,
            "kind": "tm:cloud:ltm:pool-members:ltmpoolmemberstate",
            "lastUpdateMicros": 0,
            "name": "130.127.192.133:80",
            "nodeReference": {
                "link": "http://localhost/tm/cloud/ltm/node-addresses/Common/shibsp1"
            },
            "objectId": 37232,
            "port": 80,
            "selfLink": "https://localhost/mgmt/tm/cloud/ltm/pool-members/37232",
            "statsContext": {
                "stats": [
                    {
                        "description": "availability_state: AVAIL_RED",
                        "lastUpdateMicros": 0,
                        "name": "health",
                        "updateType": "BASIC",
                        "value": 0.0
                    },
                    {
                        "description": "SERVERSIDE: pkts_in",
                        "lastUpdateMicros": 0,
                        "name": "serverside.pkts_in",
                        "updateType": "BASIC",
                        "value": 0.0
                    },
                    {
                        "description": "SERVERSIDE: pkts_out",
                        "lastUpdateMicros": 0,
                        "name": "serverside.pkts_out",
                        "updateType": "BASIC",
                        "value": 0.0
                    },
                    {
                        "description": "SERVERSIDE: bits-in",
                        "lastUpdateMicros": 0,
                        "name": "serverside.bits-in",
                        "updateType": "BASIC",
                        "value": 0.0
                    },
                    {
                        "description": "SERVERSIDE: bits-out",
                        "lastUpdateMicros": 0,
                        "name": "serverside.bits-out",
                        "updateType": "BASIC",
                        "value": 0.0
                    },
                    {
                        "description": "SERVERSIDE: cur_conns",
                        "lastUpdateMicros": 0,
                        "name": "serverside.cur_conns",
                        "updateType": "BASIC",
                        "value": 0.0
                    },
                    {
                        "description": "SERVERSIDE: max_conns",
                        "lastUpdateMicros": 0,
                        "name": "serverside.max_conns",
                        "updateType": "BASIC",
                        "value": 0.0
                    },
                    {
                        "description": "SERVERSIDE: tot_conns",
                        "lastUpdateMicros": 0,
                        "name": "serverside.tot_conns",
                        "updateType": "BASIC",
                        "value": 0.0
                    }
                ]
            }
        },
        {
            "address": "130.127.241.180",
            "description": "",
            "generation": 1,
            "kind": "tm:cloud:ltm:pool-members:ltmpoolmemberstate",
            "lastUpdateMicros": 0,
            "name": "130.127.241.180:80",
            "nodeReference": {
                "link": "http://localhost/tm/cloud/ltm/node-addresses/Common/statseeker"
            },
            "objectId": 37236,
            "port": 80,
            "selfLink": "https://localhost/mgmt/tm/cloud/ltm/pool-members/37236",
            "statsContext": {
                "stats": [
                    {
                        "description": "availability_state: AVAIL_GREEN",
                        "lastUpdateMicros": 0,
                        "name": "health",
                        "updateType": "BASIC",
                        "value": 1.0
                    },
                    {
                        "description": "SERVERSIDE: pkts_in",
                        "lastUpdateMicros": 0,
                        "name": "serverside.pkts_in",
                        "updateType": "BASIC",
                        "value": 0.0
                    },
                    {
                        "description": "SERVERSIDE: pkts_out",
                        "lastUpdateMicros": 0,
                        "name": "serverside.pkts_out",
                        "updateType": "BASIC",
                        "value": 0.0
                    },
                    {
                        "description": "SERVERSIDE: bits-in",
                        "lastUpdateMicros": 0,
                        "name": "serverside.bits-in",
                        "updateType": "BASIC",
                        "value": 0.0
                    },
                    {
                        "description": "SERVERSIDE: bits-out",
                        "lastUpdateMicros": 0,
                        "name": "serverside.bits-out",
                        "updateType": "BASIC",
                        "value": 0.0
                    },
                    {
                        "description": "SERVERSIDE: cur_conns",
                        "lastUpdateMicros": 0,
                        "name": "serverside.cur_conns",
                        "updateType": "BASIC",
                        "value": 0.0
                    },
                    {
                        "description": "SERVERSIDE: max_conns",
                        "lastUpdateMicros": 0,
                        "name": "serverside.max_conns",
                        "updateType": "BASIC",
                        "value": 0.0
                    },
                    {
                        "description": "SERVERSIDE: tot_conns",
                        "lastUpdateMicros": 0,
                        "name": "serverside.tot_conns",
                        "updateType": "BASIC",
                        "value": 0.0
                    }
                ]
            }
        },
        {
            "address": "130.127.69.75",
            "description": "",
            "generation": 1,
            "kind": "tm:cloud:ltm:pool-members:ltmpoolmemberstate",
            "lastUpdateMicros": 0,
            "name": "130.127.69.75:80",
            "nodeReference": {
                "link": "http://localhost/tm/cloud/ltm/node-addresses/Common/www.clemson.edu"
            },
            "objectId": 37240,
            "port": 80,
            "selfLink": "https://localhost/mgmt/tm/cloud/ltm/pool-members/37240",
            "statsContext": {
                "stats": [
                    {
                        "description": "availability_state: AVAIL_GREEN",
                        "lastUpdateMicros": 0,
                        "name": "health",
                        "updateType": "BASIC",
                        "value": 1.0
                    },
                    {
                        "description": "SERVERSIDE: pkts_in",
                        "lastUpdateMicros": 0,
                        "name": "serverside.pkts_in",
                        "updateType": "BASIC",
                        "value": 1958.0
                    },
                    {
                        "description": "SERVERSIDE: pkts_out",
                        "lastUpdateMicros": 0,
                        "name": "serverside.pkts_out",
                        "updateType": "BASIC",
                        "value": 2835.0
                    },
                    {
                        "description": "SERVERSIDE: bits-in",
                        "lastUpdateMicros": 0,
                        "name": "serverside.bits-in",
                        "updateType": "BASIC",
                        "value": 3084376.0
                    },
                    {
                        "description": "SERVERSIDE: bits-out",
                        "lastUpdateMicros": 0,
                        "name": "serverside.bits-out",
                        "updateType": "BASIC",
                        "value": 28411304.0
                    },
                    {
                        "description": "SERVERSIDE: cur_conns",
                        "lastUpdateMicros": 0,
                        "name": "serverside.cur_conns",
                        "updateType": "BASIC",
                        "value": 0.0
                    },
                    {
                        "description": "SERVERSIDE: max_conns",
                        "lastUpdateMicros": 0,
                        "name": "serverside.max_conns",
                        "updateType": "BASIC",
                        "value": 9.0
                    },
                    {
                        "description": "SERVERSIDE: tot_conns",
                        "lastUpdateMicros": 0,
                        "name": "serverside.tot_conns",
                        "updateType": "BASIC",
                        "value": 96.0
                    }
                ]
            }
        },
        {
            "address": "130.127.235.49",
            "description": "",
            "generation": 1,
            "kind": "tm:cloud:ltm:pool-members:ltmpoolmemberstate",
            "lastUpdateMicros": 0,
            "name": "130.127.235.49:80",
            "nodeReference": {
                "link": "http://localhost/tm/cloud/ltm/node-addresses/Common/virtual2.clemson.edu"
            },
            "objectId": 37244,
            "port": 80,
            "selfLink": "https://localhost/mgmt/tm/cloud/ltm/pool-members/37244",
            "statsContext": {
                "stats": [
                    {
                        "description": "availability_state: AVAIL_RED",
                        "lastUpdateMicros": 0,
                        "name": "health",
                        "updateType": "BASIC",
                        "value": 0.0
                    },
                    {
                        "description": "SERVERSIDE: pkts_in",
                        "lastUpdateMicros": 0,
                        "name": "serverside.pkts_in",
                        "updateType": "BASIC",
                        "value": 0.0
                    },
                    {
                        "description": "SERVERSIDE: pkts_out",
                        "lastUpdateMicros": 0,
                        "name": "serverside.pkts_out",
                        "updateType": "BASIC",
                        "value": 0.0
                    },
                    {
                        "description": "SERVERSIDE: bits-in",
                        "lastUpdateMicros": 0,
                        "name": "serverside.bits-in",
                        "updateType": "BASIC",
                        "value": 0.0
                    },
                    {
                        "description": "SERVERSIDE: bits-out",
                        "lastUpdateMicros": 0,
                        "name": "serverside.bits-out",
                        "updateType": "BASIC",
                        "value": 0.0
                    },
                    {
                        "description": "SERVERSIDE: cur_conns",
                        "lastUpdateMicros": 0,
                        "name": "serverside.cur_conns",
                        "updateType": "BASIC",
                        "value": 0.0
                    },
                    {
                        "description": "SERVERSIDE: max_conns",
                        "lastUpdateMicros": 0,
                        "name": "serverside.max_conns",
                        "updateType": "BASIC",
                        "value": 0.0
                    },
                    {
                        "description": "SERVERSIDE: tot_conns",
                        "lastUpdateMicros": 0,
                        "name": "serverside.tot_conns",
                        "updateType": "BASIC",
                        "value": 0.0
                    }
                ]
            }
        },
        {
            "address": "130.127.193.233",
            "description": "",
            "generation": 1,
            "kind": "tm:cloud:ltm:pool-members:ltmpoolmemberstate",
            "lastUpdateMicros": 0,
            "name": "130.127.193.233:80",
            "nodeReference": {
                "link": "http://localhost/tm/cloud/ltm/node-addresses/Common/130.127.193.233"
            },
            "objectId": 37248,
            "port": 80,
            "selfLink": "https://localhost/mgmt/tm/cloud/ltm/pool-members/37248",
            "statsContext": {
                "stats": [
                    {
                        "description": "availability_state: AVAIL_GREEN",
                        "lastUpdateMicros": 0,
                        "name": "health",
                        "updateType": "BASIC",
                        "value": 1.0
                    },
                    {
                        "description": "SERVERSIDE: pkts_in",
                        "lastUpdateMicros": 0,
                        "name": "serverside.pkts_in",
                        "updateType": "BASIC",
                        "value": 0.0
                    },
                    {
                        "description": "SERVERSIDE: pkts_out",
                        "lastUpdateMicros": 0,
                        "name": "serverside.pkts_out",
                        "updateType": "BASIC",
                        "value": 0.0
                    },
                    {
                        "description": "SERVERSIDE: bits-in",
                        "lastUpdateMicros": 0,
                        "name": "serverside.bits-in",
                        "updateType": "BASIC",
                        "value": 0.0
                    },
                    {
                        "description": "SERVERSIDE: bits-out",
                        "lastUpdateMicros": 0,
                        "name": "serverside.bits-out",
                        "updateType": "BASIC",
                        "value": 0.0
                    },
                    {
                        "description": "SERVERSIDE: cur_conns",
                        "lastUpdateMicros": 0,
                        "name": "serverside.cur_conns",
                        "updateType": "BASIC",
                        "value": 0.0
                    },
                    {
                        "description": "SERVERSIDE: max_conns",
                        "lastUpdateMicros": 0,
                        "name": "serverside.max_conns",
                        "updateType": "BASIC",
                        "value": 0.0
                    },
                    {
                        "description": "SERVERSIDE: tot_conns",
                        "lastUpdateMicros": 0,
                        "name": "serverside.tot_conns",
                        "updateType": "BASIC",
                        "value": 0.0
                    }
                ]
            }
        },
        {
            "address": "130.127.193.233",
            "description": "",
            "generation": 1,
            "kind": "tm:cloud:ltm:pool-members:ltmpoolmemberstate",
            "lastUpdateMicros": 0,
            "name": "130.127.193.233:443",
            "nodeReference": {
                "link": "http://localhost/tm/cloud/ltm/node-addresses/Common/130.127.193.233"
            },
            "objectId": 37251,
            "port": 443,
            "selfLink": "https://localhost/mgmt/tm/cloud/ltm/pool-members/37251",
            "statsContext": {
                "stats": [
                    {
                        "description": "availability_state: AVAIL_RED",
                        "lastUpdateMicros": 0,
                        "name": "health",
                        "updateType": "BASIC",
                        "value": 0.0
                    },
                    {
                        "description": "SERVERSIDE: pkts_in",
                        "lastUpdateMicros": 0,
                        "name": "serverside.pkts_in",
                        "updateType": "BASIC",
                        "value": 0.0
                    },
                    {
                        "description": "SERVERSIDE: pkts_out",
                        "lastUpdateMicros": 0,
                        "name": "serverside.pkts_out",
                        "updateType": "BASIC",
                        "value": 0.0
                    },
                    {
                        "description": "SERVERSIDE: bits-in",
                        "lastUpdateMicros": 0,
                        "name": "serverside.bits-in",
                        "updateType": "BASIC",
                        "value": 0.0
                    },
                    {
                        "description": "SERVERSIDE: bits-out",
                        "lastUpdateMicros": 0,
                        "name": "serverside.bits-out",
                        "updateType": "BASIC",
                        "value": 0.0
                    },
                    {
                        "description": "SERVERSIDE: cur_conns",
                        "lastUpdateMicros": 0,
                        "name": "serverside.cur_conns",
                        "updateType": "BASIC",
                        "value": 0.0
                    },
                    {
                        "description": "SERVERSIDE: max_conns",
                        "lastUpdateMicros": 0,
                        "name": "serverside.max_conns",
                        "updateType": "BASIC",
                        "value": 0.0
                    },
                    {
                        "description": "SERVERSIDE: tot_conns",
                        "lastUpdateMicros": 0,
                        "name": "serverside.tot_conns",
                        "updateType": "BASIC",
                        "value": 0.0
                    }
                ]
            }
        },
        {
            "address": "130.127.237.180",
            "description": "",
            "generation": 1,
            "kind": "tm:cloud:ltm:pool-members:ltmpoolmemberstate",
            "lastUpdateMicros": 0,
            "name": "130.127.237.180:25",
            "nodeReference": {
                "link": "http://localhost/tm/cloud/ltm/node-addresses/Common/mailclient1.clemson.edu"
            },
            "objectId": 40274,
            "port": 25,
            "selfLink": "https://localhost/mgmt/tm/cloud/ltm/pool-members/40274",
            "statsContext": {
                "stats": [
                    {
                        "description": "availability_state: AVAIL_RED",
                        "lastUpdateMicros": 0,
                        "name": "health",
                        "updateType": "BASIC",
                        "value": 0.0
                    },
                    {
                        "description": "SERVERSIDE: pkts_in",
                        "lastUpdateMicros": 0,
                        "name": "serverside.pkts_in",
                        "updateType": "BASIC",
                        "value": 8.0
                    },
                    {
                        "description": "SERVERSIDE: pkts_out",
                        "lastUpdateMicros": 0,
                        "name": "serverside.pkts_out",
                        "updateType": "BASIC",
                        "value": 0.0
                    },
                    {
                        "description": "SERVERSIDE: bits-in",
                        "lastUpdateMicros": 0,
                        "name": "serverside.bits-in",
                        "updateType": "BASIC",
                        "value": 3648.0
                    },
                    {
                        "description": "SERVERSIDE: bits-out",
                        "lastUpdateMicros": 0,
                        "name": "serverside.bits-out",
                        "updateType": "BASIC",
                        "value": 0.0
                    },
                    {
                        "description": "SERVERSIDE: cur_conns",
                        "lastUpdateMicros": 0,
                        "name": "serverside.cur_conns",
                        "updateType": "BASIC",
                        "value": 0.0
                    },
                    {
                        "description": "SERVERSIDE: max_conns",
                        "lastUpdateMicros": 0,
                        "name": "serverside.max_conns",
                        "updateType": "BASIC",
                        "value": 2.0
                    },
                    {
                        "description": "SERVERSIDE: tot_conns",
                        "lastUpdateMicros": 0,
                        "name": "serverside.tot_conns",
                        "updateType": "BASIC",
                        "value": 2.0
                    }
                ]
            }
        },
        {
            "address": "130.127.237.181",
            "description": "",
            "generation": 1,
            "kind": "tm:cloud:ltm:pool-members:ltmpoolmemberstate",
            "lastUpdateMicros": 0,
            "name": "130.127.237.181:25",
            "nodeReference": {
                "link": "http://localhost/tm/cloud/ltm/node-addresses/Common/mailclient2.clemson.edu"
            },
            "objectId": 40317,
            "port": 25,
            "selfLink": "https://localhost/mgmt/tm/cloud/ltm/pool-members/40317",
            "statsContext": {
                "stats": [
                    {
                        "description": "availability_state: AVAIL_RED",
                        "lastUpdateMicros": 0,
                        "name": "health",
                        "updateType": "BASIC",
                        "value": 0.0
                    },
                    {
                        "description": "SERVERSIDE: pkts_in",
                        "lastUpdateMicros": 0,
                        "name": "serverside.pkts_in",
                        "updateType": "BASIC",
                        "value": 0.0
                    },
                    {
                        "description": "SERVERSIDE: pkts_out",
                        "lastUpdateMicros": 0,
                        "name": "serverside.pkts_out",
                        "updateType": "BASIC",
                        "value": 0.0
                    },
                    {
                        "description": "SERVERSIDE: bits-in",
                        "lastUpdateMicros": 0,
                        "name": "serverside.bits-in",
                        "updateType": "BASIC",
                        "value": 0.0
                    },
                    {
                        "description": "SERVERSIDE: bits-out",
                        "lastUpdateMicros": 0,
                        "name": "serverside.bits-out",
                        "updateType": "BASIC",
                        "value": 0.0
                    },
                    {
                        "description": "SERVERSIDE: cur_conns",
                        "lastUpdateMicros": 0,
                        "name": "serverside.cur_conns",
                        "updateType": "BASIC",
                        "value": 0.0
                    },
                    {
                        "description": "SERVERSIDE: max_conns",
                        "lastUpdateMicros": 0,
                        "name": "serverside.max_conns",
                        "updateType": "BASIC",
                        "value": 0.0
                    },
                    {
                        "description": "SERVERSIDE: tot_conns",
                        "lastUpdateMicros": 0,
                        "name": "serverside.tot_conns",
                        "updateType": "BASIC",
                        "value": 0.0
                    }
                ]
            }
        },
        {
            "address": "130.127.237.182",
            "description": "",
            "generation": 1,
            "kind": "tm:cloud:ltm:pool-members:ltmpoolmemberstate",
            "lastUpdateMicros": 0,
            "name": "130.127.237.182:25",
            "nodeReference": {
                "link": "http://localhost/tm/cloud/ltm/node-addresses/Common/mailclient3.clemson.edu"
            },
            "objectId": 40331,
            "port": 25,
            "selfLink": "https://localhost/mgmt/tm/cloud/ltm/pool-members/40331",
            "statsContext": {
                "stats": [
                    {
                        "description": "availability_state: AVAIL_RED",
                        "lastUpdateMicros": 0,
                        "name": "health",
                        "updateType": "BASIC",
                        "value": 0.0
                    },
                    {
                        "description": "SERVERSIDE: pkts_in",
                        "lastUpdateMicros": 0,
                        "name": "serverside.pkts_in",
                        "updateType": "BASIC",
                        "value": 4.0
                    },
                    {
                        "description": "SERVERSIDE: pkts_out",
                        "lastUpdateMicros": 0,
                        "name": "serverside.pkts_out",
                        "updateType": "BASIC",
                        "value": 0.0
                    },
                    {
                        "description": "SERVERSIDE: bits-in",
                        "lastUpdateMicros": 0,
                        "name": "serverside.bits-in",
                        "updateType": "BASIC",
                        "value": 1824.0
                    },
                    {
                        "description": "SERVERSIDE: bits-out",
                        "lastUpdateMicros": 0,
                        "name": "serverside.bits-out",
                        "updateType": "BASIC",
                        "value": 0.0
                    },
                    {
                        "description": "SERVERSIDE: cur_conns",
                        "lastUpdateMicros": 0,
                        "name": "serverside.cur_conns",
                        "updateType": "BASIC",
                        "value": 0.0
                    },
                    {
                        "description": "SERVERSIDE: max_conns",
                        "lastUpdateMicros": 0,
                        "name": "serverside.max_conns",
                        "updateType": "BASIC",
                        "value": 1.0
                    },
                    {
                        "description": "SERVERSIDE: tot_conns",
                        "lastUpdateMicros": 0,
                        "name": "serverside.tot_conns",
                        "updateType": "BASIC",
                        "value": 1.0
                    }
                ]
            }
        },
        {
            "address": "130.127.237.183",
            "description": "",
            "generation": 1,
            "kind": "tm:cloud:ltm:pool-members:ltmpoolmemberstate",
            "lastUpdateMicros": 0,
            "name": "130.127.237.183:25",
            "nodeReference": {
                "link": "http://localhost/tm/cloud/ltm/node-addresses/Common/mailclient4.clemson.edu"
            },
            "objectId": 40336,
            "port": 25,
            "selfLink": "https://localhost/mgmt/tm/cloud/ltm/pool-members/40336",
            "statsContext": {
                "stats": [
                    {
                        "description": "availability_state: AVAIL_RED",
                        "lastUpdateMicros": 0,
                        "name": "health",
                        "updateType": "BASIC",
                        "value": 0.0
                    },
                    {
                        "description": "SERVERSIDE: pkts_in",
                        "lastUpdateMicros": 0,
                        "name": "serverside.pkts_in",
                        "updateType": "BASIC",
                        "value": 0.0
                    },
                    {
                        "description": "SERVERSIDE: pkts_out",
                        "lastUpdateMicros": 0,
                        "name": "serverside.pkts_out",
                        "updateType": "BASIC",
                        "value": 0.0
                    },
                    {
                        "description": "SERVERSIDE: bits-in",
                        "lastUpdateMicros": 0,
                        "name": "serverside.bits-in",
                        "updateType": "BASIC",
                        "value": 0.0
                    },
                    {
                        "description": "SERVERSIDE: bits-out",
                        "lastUpdateMicros": 0,
                        "name": "serverside.bits-out",
                        "updateType": "BASIC",
                        "value": 0.0
                    },
                    {
                        "description": "SERVERSIDE: cur_conns",
                        "lastUpdateMicros": 0,
                        "name": "serverside.cur_conns",
                        "updateType": "BASIC",
                        "value": 0.0
                    },
                    {
                        "description": "SERVERSIDE: max_conns",
                        "lastUpdateMicros": 0,
                        "name": "serverside.max_conns",
                        "updateType": "BASIC",
                        "value": 0.0
                    },
                    {
                        "description": "SERVERSIDE: tot_conns",
                        "lastUpdateMicros": 0,
                        "name": "serverside.tot_conns",
                        "updateType": "BASIC",
                        "value": 0.0
                    }
                ]
            }
        },
        {
            "address": "130.127.237.184",
            "description": "",
            "generation": 1,
            "kind": "tm:cloud:ltm:pool-members:ltmpoolmemberstate",
            "lastUpdateMicros": 0,
            "name": "130.127.237.184:25",
            "nodeReference": {
                "link": "http://localhost/tm/cloud/ltm/node-addresses/Common/mailclient5.clemson.edu"
            },
            "objectId": 40341,
            "port": 25,
            "selfLink": "https://localhost/mgmt/tm/cloud/ltm/pool-members/40341",
            "statsContext": {
                "stats": [
                    {
                        "description": "availability_state: AVAIL_RED",
                        "lastUpdateMicros": 0,
                        "name": "health",
                        "updateType": "BASIC",
                        "value": 0.0
                    },
                    {
                        "description": "SERVERSIDE: pkts_in",
                        "lastUpdateMicros": 0,
                        "name": "serverside.pkts_in",
                        "updateType": "BASIC",
                        "value": 0.0
                    },
                    {
                        "description": "SERVERSIDE: pkts_out",
                        "lastUpdateMicros": 0,
                        "name": "serverside.pkts_out",
                        "updateType": "BASIC",
                        "value": 0.0
                    },
                    {
                        "description": "SERVERSIDE: bits-in",
                        "lastUpdateMicros": 0,
                        "name": "serverside.bits-in",
                        "updateType": "BASIC",
                        "value": 0.0
                    },
                    {
                        "description": "SERVERSIDE: bits-out",
                        "lastUpdateMicros": 0,
                        "name": "serverside.bits-out",
                        "updateType": "BASIC",
                        "value": 0.0
                    },
                    {
                        "description": "SERVERSIDE: cur_conns",
                        "lastUpdateMicros": 0,
                        "name": "serverside.cur_conns",
                        "updateType": "BASIC",
                        "value": 0.0
                    },
                    {
                        "description": "SERVERSIDE: max_conns",
                        "lastUpdateMicros": 0,
                        "name": "serverside.max_conns",
                        "updateType": "BASIC",
                        "value": 0.0
                    },
                    {
                        "description": "SERVERSIDE: tot_conns",
                        "lastUpdateMicros": 0,
                        "name": "serverside.tot_conns",
                        "updateType": "BASIC",
                        "value": 0.0
                    }
                ]
            }
        },
        {
            "address": "130.127.237.186",
            "description": "",
            "generation": 1,
            "kind": "tm:cloud:ltm:pool-members:ltmpoolmemberstate",
            "lastUpdateMicros": 0,
            "name": "130.127.237.186:25",
            "nodeReference": {
                "link": "http://localhost/tm/cloud/ltm/node-addresses/Common/mailclient6.clemson.edu"
            },
            "objectId": 40346,
            "port": 25,
            "selfLink": "https://localhost/mgmt/tm/cloud/ltm/pool-members/40346",
            "statsContext": {
                "stats": [
                    {
                        "description": "availability_state: AVAIL_RED",
                        "lastUpdateMicros": 0,
                        "name": "health",
                        "updateType": "BASIC",
                        "value": 0.0
                    },
                    {
                        "description": "SERVERSIDE: pkts_in",
                        "lastUpdateMicros": 0,
                        "name": "serverside.pkts_in",
                        "updateType": "BASIC",
                        "value": 0.0
                    },
                    {
                        "description": "SERVERSIDE: pkts_out",
                        "lastUpdateMicros": 0,
                        "name": "serverside.pkts_out",
                        "updateType": "BASIC",
                        "value": 0.0
                    },
                    {
                        "description": "SERVERSIDE: bits-in",
                        "lastUpdateMicros": 0,
                        "name": "serverside.bits-in",
                        "updateType": "BASIC",
                        "value": 0.0
                    },
                    {
                        "description": "SERVERSIDE: bits-out",
                        "lastUpdateMicros": 0,
                        "name": "serverside.bits-out",
                        "updateType": "BASIC",
                        "value": 0.0
                    },
                    {
                        "description": "SERVERSIDE: cur_conns",
                        "lastUpdateMicros": 0,
                        "name": "serverside.cur_conns",
                        "updateType": "BASIC",
                        "value": 0.0
                    },
                    {
                        "description": "SERVERSIDE: max_conns",
                        "lastUpdateMicros": 0,
                        "name": "serverside.max_conns",
                        "updateType": "BASIC",
                        "value": 0.0
                    },
                    {
                        "description": "SERVERSIDE: tot_conns",
                        "lastUpdateMicros": 0,
                        "name": "serverside.tot_conns",
                        "updateType": "BASIC",
                        "value": 0.0
                    }
                ]
            }
        }
    ],
    "kind": "tm:cloud:ltm:pool-members:ltmpoolmembercollectionstate",
    "lastUpdateMicros": 0,
    "selfLink": "https://localhost/mgmt/tm/cloud/ltm/pool-members"
}
